README.rst
setup.cfg
setup.py
fact/VERSION
fact/__init__.py
fact/encrypt_credentials.py
fact/io.py
fact/path.py
fact/qla.py
fact/time.py
fact/analysis/__init__.py
fact/analysis/binning.py
fact/analysis/core.py
fact/analysis/source.py
fact/analysis/statistics.py
fact/analysis/scripts/__init__.py
fact/analysis/scripts/radec.py
fact/analysis/scripts/theta.py
fact/auxservices/__init__.py
fact/auxservices/base.py
fact/auxservices/services.py
fact/coordinates/__init__.py
fact/coordinates/camera_frame.py
fact/coordinates/representation.py
fact/coordinates/utils.py
fact/credentials/__init__.py
fact/credentials/credentials.encrypted
fact/factdb/__init__.py
fact/factdb/database.py
fact/factdb/models.py
fact/factdb/utils.py
fact/instrument/__init__.py
fact/instrument/camera.py
fact/instrument/constants.py
fact/instrument/trigger.py
fact/plotting/__init__.py
fact/plotting/analysis.py
fact/plotting/core.py
fact/plotting/utils.py
fact/resources/FACTmap111030.txt
fact/resources/known_problems_from_trac.txt
fact/resources/pixel-map.csv
pyfact.egg-info/PKG-INFO
pyfact.egg-info/SOURCES.txt
pyfact.egg-info/dependency_links.txt
pyfact.egg-info/entry_points.txt
pyfact.egg-info/not-zip-safe
pyfact.egg-info/requires.txt
pyfact.egg-info/top_level.txt