Metadata-Version: 1.0
Name: pyfact
Version: 0.26.2
Summary: A module containing useful methods for working with fact
Home-page: http://github.com/fact-project/pyfact
Author: Maximilian Noethe, Dominik Neise
Author-email: maximilian.noethe@tu-dortmund.de
License: MIT
Platform: UNKNOWN
